try_pp_test/__init__.py
try_pp_test-0.1.0.dist-info/METADATA
try_pp_test-0.1.0.dist-info/WHEEL
try_pp_test-0.1.0.dist-info/RECORD
